CoderElijah/E.py
CoderElijah/__init__.py
CoderElijah/rickPy.py
coderelijahbeta-0.2.5.dist-info/LICENSE
coderelijahbeta-0.2.5.dist-info/WHEEL
coderelijahbeta-0.2.5.dist-info/METADATA
coderelijahbeta-0.2.5.dist-info/RECORD
